dlmy/__init__.py
dlmy/__main__.py
dlmy/configuration.py
dlmy/download.py
dlmy/search.py
dlmy-2.9.dist-info/entry_points.txt
dlmy-2.9.dist-info/LICENSE
dlmy-2.9.dist-info/WHEEL
dlmy-2.9.dist-info/METADATA
dlmy-2.9.dist-info/RECORD
