Metadata-Version: 2.1
Name: dlmy
Version: 2.9
Summary: Yet another Spotify Downloader ...
License: MIT
Author: yrwq
Author-email: yrwqid@gmail.com
Requires-Python: >=3.9,<4.0
Classifier: License :: OSI Approved :: MIT License
Classifier: Programming Language :: Python :: 3
Classifier: Programming Language :: Python :: 3.9
Requires-Dist: beautifulsoup4 (>=4.9.3,<5.0.0)
Requires-Dist: colorama (>=0.4.4,<0.5.0)
Requires-Dist: configparser (>=5.0.1,<6.0.0)
Requires-Dist: lxml (>=4.6.2,<5.0.0)
Requires-Dist: requests (>=2.25.1,<3.0.0)
Requires-Dist: youtube_dl (>=2021.1.8,<2022.0.0)
